<?xml version="1.0" encoding="UTF-8"?>
<plugin version="1">
<name> AIS Radar view </name>
<version> 1.4.3.0 </version>
<release> 0 </release>
<summary> AIS Radar view Plugin </summary>

<api-version> 1.16 </api-version>
<open-source> yes </open-source>
<author> Johan Sman </author>
<source> https://github.com/rgleason/AISradar_pi </source>

<description>
Radar PlugIn for OpenCPN Shows AIS targets in a radar style view.
</description>

<target>debian-armhf</target>
<build-target>debian</build-target>
<build-gtk></build-gtk>
<target-version>12</target-version>
<target-arch>armhf</target-arch>
<tarball-url>
https://dl.cloudsmith.io/public/opencpn/aisradar-beta/raw/names/aisradar_pi-1.4.3.0-debian-armhf-12-bookworm-armhf-tarball/versions/v1.4.3.0/aisradar_pi-1.4.3.0-debian-armhf-12-bookworm-armhf.tar.gz
</tarball-url>
<info-url> https://opencpn.org/OpenCPN/plugins/aisradarview.html </info-url>
</plugin>
