<?xml version="1.0" encoding="UTF-8"?>
<!-- https://circleci.com/gh/Rasbats/CanadianTides_pi/867 -->
<plugin version="1">
  <name> CanadianTides </name>
  <version> v0.9.5 </version>
  <release> 0 </release>
  <summary> Show Canadian tidal heights for LW/HW </summary>

  <api-version> 1.18 </api-version>
  <open-source> yes </open-source>
  <author> Mike Rossiter </author>
  <source> https://github.com/Rasbats/CanadianTides_pi </source>
  <info-url> https://opencpn.org/OpenCPN/plugins/CanadianTides.html </info-url>

  <description> Show Canadian Tides (HW/LW) at over 600 ports.
 </description>

  <target>android-arm64</target>
  <target-version>16</target-version>
  <target-arch>arm64</target-arch>
  <tarball-url> https://dl.cloudsmith.io/public/opencpn/canadiantides-prod/raw/names/CanadianTides-v0.9.5-android-arm64-A64-16-tarball/versions/v0.9.5/CanadianTides-v0.9.5_android-arm64-16-arm64.tar.gz </tarball-url>
  <tarball-checksum> 7cee143619422e01ea8a60f4b2f5cf5081bddc79c36c3a82a02624874d60d39b </tarball-checksum>
</plugin>
