<?xml version="1.0" encoding="UTF-8"?>
<!-- https://circleci.com/gh/Rasbats/CanadianTides_pi/393 -->
<plugin version="1">
  <name> CanadianTides </name>
  <version> v0.6.0 </version>
  <release>  </release>
  <summary> Show Canadian tidal heights for LW/HW </summary>

  <api-version> 1.17 </api-version>
  <open-source> yes </open-source>
  <author> Mike Rossiter </author>
  <source> https://github.com/Rasbats/CanadianTides_pi </source>
  <info-url> https://opencpn.org/OpenCPN/plugins/CanadianTides.html </info-url>

  <description> Show Canadian Tides (HW/LW) at over 600 ports.
 </description>

  <target>ubuntu-gtk3-x86_64</target>
  <target-version>18.04</target-version>
  <target-arch>x86_64</target-arch>
  <tarball-url> https://dl.cloudsmith.io/public/opencpn/canadiantides-prod/raw/names/CanadianTides-v0.6.0-ubuntu-gtk3-18.04-tarball/versions/v0.6.0/CanadianTides-v0.6.0_ubuntu-gtk3-18.04-x86_64.tar.gz </tarball-url>
  <tarball-checksum> c20a5d876cd5f3502ca6f0825ead54b5dd661b2f3be78c9304e53eb321e32e77 </tarball-checksum>
</plugin>
