<?xml version="1.0" encoding="UTF-8"?>
<!-- https://circleci.com/gh/Rasbats/EarthExplorer_pi/159 -->
<plugin version="1">
  <name> EarthExplorer </name>
  <version> v1.0.0 </version>
  <release>  </release>
  <summary> Connect ship with Google Earth </summary>

  <api-version> 1.16 </api-version>
  <open-source> yes </open-source>
  <author> Mike Rossiter </author>
  <source> https://github.com/Rasbats/EarthExplorer_pi </source>
  <info-url> https://opencpn.org/OpenCPN/plugins/EarthExplorer.html </info-url>

  <description> Connect ship with Google Earth
 </description>

  <target>ubuntu-x86_64</target>
  <target-version>16.04</target-version>
  <target-arch>x86_64</target-arch>
  <tarball-url> https://dl.cloudsmith.io/public/opencpn/earthexplorer-prod/raw/names/EarthExplorer-v1.0.0-ubuntu-16.04-tarball/versions/v1.0.0/EarthExplorer-v1.0.0_ubuntu-16.04-x86_64.tar.gz </tarball-url>
  <tarball-checksum> 24dee01aae46da44a0494b9994c736e4bf4c145f0465afd89469637cb949191d </tarball-checksum>
</plugin>
