<?xml version="1.0" encoding="UTF-8"?>
<!--  -->
<plugin version="1">
  <name> frcurrents </name>
  <version> v1.13.0 </version>
  <release> 0 </release>
  <summary> French Tidal Currents </summary>

  <api-version> 1.16 </api-version>
  <open-source> yes </open-source>
  <author> Mike Rossiter </author>
  <source> https://github.com/Rasbats/frcurrents_pi </source>
  <info-url> https://opencpn.org/OpenCPN/plugins/frcurrents.html </info-url>

  <description> Shows French Tidal Currents.
 </description>

  <target>debian-armhf</target>
  <target-version>11</target-version>
  <target-arch>armhf</target-arch>
  <tarball-url> https://dl.cloudsmith.io/public/opencpn/frcurrents-prod/raw/names/frcurrents-v1.13.0-debian-armhf-A32-11-tarball/versions/v1.13.0/frcurrents-v1.13.0_debian-armhf-11-armhf.tar.gz </tarball-url>
  <tarball-checksum> 2b657c720e468e33bf7c86c2b09ea8d622a2f509d450c4e991a4fa1e87ef50b7 </tarball-checksum>
</plugin>
