<?xml version="1.0" encoding="UTF-8"?>
<!-- https://circleci.com/gh/nohal/nsk_pi/416 -->
<plugin version="1">
  <name> NSK </name>
  <version> v0.2.1 </version>
  <release>  </release>
  <summary> NMEA0183 to SignalK converter plugin for OpenCPN </summary>

  <api-version> 1.18 </api-version>
  <open-source> yes </open-source>
  <author> Pavel Kalian </author>
  <source> https://github.com/nohal/nsk_pi </source>
  <info-url> https://opencpn.org/OpenCPN/plugins/nsk.html </info-url>

  <description>   NMEA0183 to SignalK converter plugin for OpenCPN
 </description>

  <target>flatpak-x86_64</target>
  <target-version>22.08</target-version>
  <target-arch>x86_64</target-arch>
  <tarball-url> https://dl.cloudsmith.io/public/nohal/nsk_pi-stable/raw/names/NSK-v0.2.1-flatpak-22.08-tarball/versions/v0.2.1/NSK-v0.2.1_flatpak-22.08-x86_64.tar.gz </tarball-url>
  <tarball-checksum> 733cf61d3e8265c5a113f9404f66ff3b0a02d3d1a2eeaca722577785de5f9465 </tarball-checksum>
</plugin>
