<?xml version="1.0" encoding="UTF-8"?>
<!--  -->
<plugin version="1">
  <name> otcurrent </name>
  <version> v4.5.3 </version>
  <release> 0 </release>
  <summary> Predict future tidal currents </summary>

  <api-version> 1.18 </api-version>
  <open-source> yes </open-source>
  <author> Mike Rossiter </author>
  <source> https://github.com/Rasbats/otcurrent_pi </source>
  <info-url> https://opencpn.org/OpenCPN/plugins/otcurrent.html </info-url>

  <description> Allows predictions of future tidal currents, based on the harmonics data in
OpenCPN.
 </description>

  <target>debian-armhf</target>
  <target-version>13</target-version>
  <target-arch>armhf</target-arch>
  <tarball-url> https://dl.cloudsmith.io/public/opencpn/otcurrent-prod/raw/names/otcurrent-v4.5.3-debian-armhf-A32-13-tarball/versions/v4.5.3/otcurrent-v4.5.3_debian-armhf-13-armhf.tar.gz </tarball-url>
  <tarball-checksum> 724145816d5b3aa6c1d0490e61334193d3904029fdd4145b2486a4d5a9e2da2f </tarball-checksum>
</plugin>
