<?xml version="1.0" encoding="UTF-8"?>
<!-- https://circleci.com/gh/Rasbats/otcurrent_pi/5544 -->
<plugin version="1">
  <name> otcurrent </name>
  <version> 4.5.2+5544.c935c00 </version>
  <release> 0 </release>
  <summary> Predict future tidal currents </summary>

  <api-version> 1.18 </api-version>
  <open-source> yes </open-source>
  <author> Mike Rossiter </author>
  <source> https://github.com/Rasbats/otcurrent_pi </source>
  <info-url> https://opencpn.org/OpenCPN/plugins/otcurrent.html </info-url>

  <description> Allows predictions of future tidal currents, based on the harmonics data in
OpenCPN.
 </description>

  <target>debian-x86_64</target>
  <target-version>11</target-version>
  <target-arch>x86_64</target-arch>
  <tarball-url> https://dl.cloudsmith.io/public/opencpn/otcurrent-alpha/raw/names/otcurrent-4.5-debian-x86_64-11-tarball/versions/4.5.2+5544.c935c00/otcurrent-4.5.2+5544.c935c00_debian-x86_64-11-x86_64.tar.gz </tarball-url>
  <tarball-checksum> c0e681fba39b1145e8323ab14934802966486930fb1df4a2c07c0dc4d0f1e0e1 </tarball-checksum>
</plugin>
