<?xml version="1.0" encoding="UTF-8"?>
<!-- https://circleci.com/gh/nohal/projections_pi/67 -->
<plugin version="1">
  <name> Projections </name>
  <version> v0.3.0 </version>
  <release>  </release>
  <summary> NMEA0183 to SignalK converter </summary>

  <api-version> 1.18 </api-version>
  <open-source> yes </open-source>
  <author> Sean D'Epagnier </author>
  <source> https://github.com/nohal/projections_pi </source>
  <info-url> https://opencpn.org/OpenCPN/plugins/projections.html </info-url>

  <description>   NMEA0183 to SignalK converter
 </description>

  <target>debian-x86_64</target>
  <target-version>11</target-version>
  <target-arch>x86_64</target-arch>
  <tarball-url> https://dl.cloudsmith.io/public/nohal/projections_pi-stable/raw/names/Projections-v0.3.0-debian-11-tarball/versions/v0.3.0/Projections-v0.3.0_debian-11-x86_64.tar.gz </tarball-url>
  <tarball-checksum> f9750e67d8d53bd662a197b8b5d5d7c84cced5a1073b407861e3ca9971da8a32 </tarball-checksum>
</plugin>
