<?xml version="1.0" encoding="UTF-8"?>
<!-- https://circleci.com/gh/rgleason/vdr_pi/1869 -->
<plugin version="1">
  <name> VDR </name>
  <version> v1.3.25 </version>
  <release> 0 </release>
  <summary> Voyage Data Recorder </summary>

  <api-version> 1.16 </api-version>
  <open-source> yes </open-source>
  <author> Rick Gleason </author>
  <source>  </source>
  <info-url> https://opencpn.org/OpenCPN/plugins/vdr.html </info-url>

  <description> A Voyage Data Recorder (VDR) to record and play NMEA files.
Save NMEA stream to a file.  Replay NMEA stream previously saved. Used to test plugins.
 </description>

  <target>flatpak-x86_64</target>
  <target-version>20.08</target-version>
  <target-arch>x86_64</target-arch>
  <tarball-url> https://dl.cloudsmith.io/public/opencpn/vdr-prod/raw/names/VDR-v1.3.25-flatpak-20.08-tarball/versions/v1.3.25/VDR-v1.3.25_flatpak-20.08-x86_64.tar.gz </tarball-url>
  <tarball-checksum> 1ac231bede0576cfcf470b0d47f2c7dff1731617db171544dc60257355dc1cbc </tarball-checksum>
</plugin>
