<?xml version="1.0" encoding="UTF-8"?>
<plugin version="1">
  <name> VDR </name>
  <version> 1.3.7.0-+139.v1.3.7.0 </version>
  <release> 0 </release>
  <summary> Voyage Data Recorder </summary>

  <api-version> 1.16 </api-version>
  <open-source> yes </open-source>
  <author> Rick Gleason </author>
  <source> https://github.com/rgleason/vdr_pi </source>
  <info-url> https://opencpn.org/OpenCPN/plugins/vdr.html </info-url>

  <description> A Voyage Data Recorder (VDR) to record and play NMEA files.
Save NMEA stream to a file.  Replay NMEA stream previously saved.
 </description>

  <target>msvc</target>
  <target-version>10.0.14393</target-version>
  <target-arch>x86_64</target-arch>
  <tarball-url> https://dl.cloudsmith.io/public/opencpn/vdr-prod/raw/names/VDR-1.3-msvc-10.0.14393-tarball/versions/1.3.7.0-+139.v1.3.7.0/VDR-1.3.7.0-+139.v1.3.7.0_msvc-10.0.14393-win32.tar.gz </tarball-url>
  <tarball-checksum> 4004ca6b79d64da021cd121ca0505c71eb4efa54f5cf8f26c409bb6a52cd4bf5 </tarball-checksum>
</plugin>
